[
  {
    "Parameter": "market_id",
    "Type": "string",
    "Description": "the market ID"
  },
  {
    "Parameter": "is_buy",
    "Type": "bool",
    "Description": "whether the trade is a buy or sell"
  },
  {
    "Parameter": "executionType",
    "Type": "string",
    "Description": "the execution type"
  },
  {
    "Parameter": "subaccount_id",
    "Type": "string",
    "Description": "the subaccount ID"
  },
  {
    "Parameter": "position_delta",
    "Type": "types.PositionDelta",
    "Description": "the position delta of the trade"
  },
  {
    "Parameter": "payout",
    "Type": "cosmossdk_io_math.LegacyDec",
    "Description": "the payout of the trade"
  },
  {
    "Parameter": "fee",
    "Type": "cosmossdk_io_math.LegacyDec",
    "Description": "the fee of the trade"
  },
  {
    "Parameter": "order_hash",
    "Type": "string",
    "Description": "the order hash"
  },
  {
    "Parameter": "fee_recipient_address",
    "Type": "string",
    "Description": "the fee recipient address"
  },
  {
    "Parameter": "cid",
    "Type": "string",
    "Description": "the client order ID"
  },
  {
    "Parameter": "trade_id",
    "Type": "string",
    "Description": "the trade ID"
  }
]
