[
  {
    "Parameter": "title",
    "Type": "string",
    "Description": "Title is a short summary"
  },
  {
    "Parameter": "description",
    "Type": "string",
    "Description": "Description is a human readable text"
  },
  {
    "Parameter": "run_as",
    "Type": "string",
    "Description": "RunAs is the address that is passed to the contract's enviroment as sender"
  },
  {
    "Parameter": "admin",
    "Type": "string",
    "Description": "Admin is an optional address that can execute migrations"
  },
  {
    "Parameter": "code_id",
    "Type": "uint64",
    "Description": "CodeID is the reference to the stored WASM code"
  },
  {
    "Parameter": "label",
    "Type": "string",
    "Description": "Label is optional metadata to be stored with a constract instance."
  },
  {
    "Parameter": "msg",
    "Type": "RawContractMessage",
    "Description": "Msg json encode message to be passed to the contract on instantiation"
  },
  {
    "Parameter": "funds",
    "Type": "github_com_cosmos_cosmos_sdk_types.Coins",
    "Description": "Funds coins that are transferred to the contract on instantiation"
  },
  {
    "Parameter": "salt",
    "Type": "byte array",
    "Description": "Salt is an arbitrary value provided by the sender. Size can be 1 to 64."
  },
  {
    "Parameter": "fix_msg",
    "Type": "bool",
    "Description": "FixMsg include the msg value into the hash for the predictable address. Default is false"
  }
]
