[
  {
    "Parameter": "cumulative_funding",
    "Type": "string",
    "Description": "Defines the cumulative funding of a perpetual market."
  },
  {
    "Parameter": "cumulative_price",
    "Type": "string",
    "Description": "Defines defines the cumulative price for the current hour up to the last timestamp."
  },
  {
    "Parameter": "last_timestamp",
    "Type": "int64",
    "Description": "Defines the last funding timestamp in seconds of a perpetual market in UNIX seconds."
  },
  {
    "Parameter": "last_funding_rate",
    "Type": "string",
    "Description": "Defines the last funding rate of a perpetual market."
  }
]
